PYTHON_PACKAGE/__init__.py
PYTHON_PACKAGE/__main__.py
PYTHON_PACKAGE/test/__init__.py
PYTHON_PACKAGE/test/test_doctest.py
PYTHON_PACKAGE/test/test_example.py
PYTHON_PACKAGE/test/test_notebook.py
PYTHON_PACKAGE/test/data/__init__.py
PYTHON_PACKAGE/test/data/data.txt
wingechr_PYTHON_PACKAGE-0.0.3.dist-info/LICENSE
wingechr_PYTHON_PACKAGE-0.0.3.dist-info/METADATA
wingechr_PYTHON_PACKAGE-0.0.3.dist-info/WHEEL
wingechr_PYTHON_PACKAGE-0.0.3.dist-info/entry_points.txt
wingechr_PYTHON_PACKAGE-0.0.3.dist-info/top_level.txt
wingechr_PYTHON_PACKAGE-0.0.3.dist-info/RECORD
